openinference/instrumentation/crewai/__init__.py
openinference/instrumentation/crewai/_wrappers.py
openinference/instrumentation/crewai/version.py
openinference_instrumentation_crewai-0.1.17.dist-info/METADATA
openinference_instrumentation_crewai-0.1.17.dist-info/WHEEL
openinference_instrumentation_crewai-0.1.17.dist-info/entry_points.txt
openinference_instrumentation_crewai-0.1.17.dist-info/licenses/LICENSE
openinference_instrumentation_crewai-0.1.17.dist-info/RECORD
