Metadata-Version: 2.4
Name: openinference-instrumentation-crewai
Version: 0.1.17
Summary: OpenInference Crewai Instrumentation
Project-URL: Homepage, https://github.com/Arize-ai/openinference/tree/main/python/instrumentation/openinference-instrumentation-crewai
Author-email: OpenInference Authors <oss@arize.com>
License-Expression: Apache-2.0
License-File: LICENSE
Classifier: Development Status :: 5 - Production/Stable
Classifier: Intended Audience :: Developers
Classifier: License :: OSI Approved :: Apache Software License
Classifier: Programming Language :: Python
Classifier: Programming Language :: Python :: 3
Classifier: Programming Language :: Python :: 3.10
Classifier: Programming Language :: Python :: 3.11
Classifier: Programming Language :: Python :: 3.12
Classifier: Programming Language :: Python :: 3.13
Requires-Python: <3.14,>=3.10
Requires-Dist: openinference-instrumentation>=0.1.27
Requires-Dist: openinference-semantic-conventions>=0.1.21
Requires-Dist: opentelemetry-api
Requires-Dist: opentelemetry-instrumentation
Requires-Dist: opentelemetry-semantic-conventions
Requires-Dist: typing-extensions
Requires-Dist: wrapt
Provides-Extra: instruments
Requires-Dist: crewai>=0.119.0; extra == 'instruments'
Provides-Extra: test
Requires-Dist: crewai==0.119.0; extra == 'test'
Requires-Dist: opentelemetry-sdk; extra == 'test'
Requires-Dist: pytest-vcr; extra == 'test'
Requires-Dist: responses; extra == 'test'
